[
  {
    "id": 1,
    "title": "Administrative Officer",
    "content": "Sprain of deltoid ligament of left ankle",
    "writer": "Gösta",
    "created_data": "2022-06-22",
    "modified_data": "2022-07-19",
    "user_id": 2466
  },
  {
    "id": 2,
    "title": "Programmer II",
    "content": "Nondisp commnt fx shaft of r tibia, 7thE",
    "writer": "Andréanne",
    "created_data": "2022-06-22",
    "modified_data": "2022-07-20",
    "user_id": 1021
  },
  {
    "id": 3,
    "title": "Programmer I",
    "content": "Inj unsp musc/fasc/tend at thigh level, unsp thigh, subs",
    "writer": "Östen",
    "created_data": "2022-07-13",
    "modified_data": "2022-07-20",
    "user_id": 3472
  },
  {
    "id": 4,
    "title": "Paralegal",
    "content": "Oth incomplete lesion at C7, subs",
    "writer": "Maëlyss",
    "created_data": "2022-07-08",
    "modified_data": "2022-07-20",
    "user_id": 3743
  },
  {
    "id": 5,
    "title": "Web Designer II",
    "content": "Fall from non-moving wheelchair, initial encounter",
    "writer": "Marie-ève",
    "created_data": "2022-06-24",
    "modified_data": "2022-07-19",
    "user_id": 8508
  },
  {
    "id": 6,
    "title": "Actuary",
    "content": "Superficial frostbite of unspecified ankle, sequela",
    "writer": "Naéva",
    "created_data": "2022-07-06",
    "modified_data": "2022-07-20",
    "user_id": 7493
  },
  {
    "id": 7,
    "title": "Librarian",
    "content": "Fracture of bony thorax, part unsp, subs for fx w routn heal",
    "writer": "Bérangère",
    "created_data": "2022-07-13",
    "modified_data": "2022-07-19",
    "user_id": 4251
  }
]
